pyDVC.py
pyDVC-1.0.dist-info/LICENSE
pyDVC-1.0.dist-info/METADATA
pyDVC-1.0.dist-info/WHEEL
pyDVC-1.0.dist-info/top_level.txt
pyDVC-1.0.dist-info/RECORD
