Metadata-Version: 2.1
Name: pyDVC
Version: 1.0
Summary: Python implementation of Discrete Voronoi Chain algorithm by Mirko Velić, Dave May & Louis Moresi (2009).
Home-page: https://github.com/jadball/pyDVC
Author: James Ball
Author-email: jadball@gmail.com
License: BSD 3-Clause
Classifier: Programming Language :: Python :: 3
Classifier: License :: OSI Approved :: BSD License
Classifier: Operating System :: OS Independent
Requires-Python: >=3.6
License-File: LICENSE
Requires-Dist: numpy
Requires-Dist: numba
